main.py
mseep_dune_analytics_mcp-0.1.1.dist-info/licenses/LICENSE
mseep_dune_analytics_mcp-0.1.1.dist-info/METADATA
mseep_dune_analytics_mcp-0.1.1.dist-info/WHEEL
mseep_dune_analytics_mcp-0.1.1.dist-info/entry_points.txt
mseep_dune_analytics_mcp-0.1.1.dist-info/top_level.txt
mseep_dune_analytics_mcp-0.1.1.dist-info/RECORD
