Metadata-Version: 2.4
Name: mseep-dune-analytics-mcp
Version: 0.1.1
Summary: A mcp server that bridges Dune Analytics data to AI agents.
Author-email: mseep <support@skydeck.ai>
Requires-Python: >=3.13
License-File: LICENSE
Requires-Dist: mcp[cli]>=1.4.1
Requires-Dist: pandas>=2.2.3
Dynamic: license-file
